{
  "cars": [
    {
      "id": 1,
      "name": "Toyota Camry",
      "price": 24970,
      "image": "http://localhost:4200/images/1.jpeg"
    },
    {
      "id": 2,
      "name": "Honda Civic",
      "price": 22545,
      "image": "http://localhost:4200/images/2.jpeg"
    },
    {
      "id": 3,
      "name": "Ford Mustang",
      "price": 28840,
      "image": "http://localhost:4200/images/3.jpeg"
    },
    {
      "id": 4,
      "name": "Chevrolet Corvette",
      "price": 62195,
      "image": "http://localhost:4200/images/4.jpeg"
    },
    {
      "id": 5,
      "name": "Tesla Model S",
      "price": 79990,
      "image": "http://localhost:4200/images/5.jpeg"
    },
    {
      "id": 6,
      "name": "BMW 3 Series",
      "price": 43700,
      "image": "http://localhost:4200/images/6.jpeg"
    },
    {
      "id": 7,
      "name": "Audi A4",
      "price": 40145,
      "image": "http://localhost:4200/images/7.jpeg"
    },
    {
      "id": 8,
      "name": "Mercedes-Benz C-Class",
      "price": 43600,
      "image": "http://localhost:4200/images/8.jpeg"
    },
    {
      "id": 9,
      "name": "McLaren 600LT",
      "price": 300000,
      "image": "http://localhost:4200/images/9.jpeg"
    }
  ]
}